{
  "critical_path_cost": 19,
  "diagnostics": [
    {
      "blocking": true,
      "details": {
        "source_text": "for (int i = 0; i < slot_size; i++)\n    {\n        idxF[i] = i;\n    }"
      },
      "reason": "unsupported dynamic loop boundary",
      "severity": "error",
      "source_span": {
        "end": {
          "column": 5,
          "line": 201,
          "offset": 4769
        },
        "file": "/home/guoshuai/github/poseidon/Trident/knn/sort_base_rank.cpp",
        "start": {
          "column": 5,
          "line": 198,
          "offset": 4702
        }
      },
      "stmt_id": "sign@4702",
      "suggested_fallback": "skip rewrite for this region"
    }
  ],
  "edges": 16,
  "entry_function": "cmp",
  "frontend": "textual_fallback",
  "layers": [
    "layer 0: op0",
    "layer 1: op1",
    "layer 2: op2",
    "layer 3: op3",
    "layer 4: op4",
    "layer 5: op5"
  ],
  "max_parallel_width": 1,
  "ops": 6,
  "rewrite_status": "blocked",
  "schema_version": 2,
  "source_file": "/home/guoshuai/github/poseidon/Trident/knn/sort_base_rank.cpp",
  "values": 23
}
